{
  "file_id": "c21967c2-22ed-4838-9337-f48d59ad03ca",
  "image_path": "/home/jaeho/projects_linux/ecoguide.v1/uploads/user_images/c21967c2-22ed-4838-9337-f48d59ad03ca.jpg",
  "timestamp": "2025-10-26T21:45:48.240826",
  "classification": {
    "primary_category": "가전",
    "primary_category_name": "가전",
    "secondary_category": "기타 가전",
    "secondary_category_name": "선풍기",
    "object_name": "선풍기"
  },
  "dimensions": {
    "w_cm": 30,
    "h_cm": 100,
    "d_cm": 30
  },
  "confidence": 0.8,
  "reasoning": "주어진 이미지에서 선풍기가 보이며, 해당 품목은 전기 제품으로 '기타 가전'에 해당합니다.",
  "user_feedback": {
    "notes": "",
    "timestamp": "2025-10-26T21:45:48.137851"
  },
  "metadata": {
    "labeling_quality": 0.6200000000000001
  }
}